topsis/__init__.py
topsis/result.csv
topsis/sample-data.csv
topsis/topsis.py
topsis_mridul-1.0.0.dist-info/licenses/LICENSE
topsis_mridul-1.0.0.dist-info/METADATA
topsis_mridul-1.0.0.dist-info/WHEEL
topsis_mridul-1.0.0.dist-info/entry_points.txt
topsis_mridul-1.0.0.dist-info/top_level.txt
topsis_mridul-1.0.0.dist-info/RECORD
