Metadata-Version: 2.4
Name: topsis-Mridul
Version: 1.0.0
Summary: A Python implementation of the TOPSIS decision-making method
Home-page: https://github.com/mridulmahajan04/Topsis_Package/
Author: Mridul Mahajan
Author-email: Mridul Mahajan <mridulmahajan16@gmail.com>
Maintainer-email: Mridul Mahajan <mridulmahajan16@gmail.com>
License: MIT
Project-URL: Homepage, https://github.com/mridulmahajan04/Topsis_Package/
Project-URL: Repository, https://github.com/mridulmahajan04/Topsis_Package/
Project-URL: Bug Tracker, https://github.com/mridulmahajan04/Topsis_Package/issues
Keywords: topsis,decision-making,multi-criteria,ranking,optimization
Classifier: Development Status :: 4 - Beta
Classifier: Intended Audience :: Science/Research
Classifier: License :: OSI Approved :: MIT License
Classifier: Operating System :: OS Independent
Classifier: Programming Language :: Python :: 3
Classifier: Programming Language :: Python :: 3.6
Classifier: Programming Language :: Python :: 3.7
Classifier: Programming Language :: Python :: 3.8
Classifier: Programming Language :: Python :: 3.9
Classifier: Programming Language :: Python :: 3.10
Classifier: Programming Language :: Python :: 3.11
Classifier: Topic :: Scientific/Engineering :: Mathematics
Classifier: Topic :: Software Development :: Libraries :: Python Modules
Requires-Python: >=3.6
License-File: LICENSE
Requires-Dist: numpy>=1.19.0
Requires-Dist: pandas>=1.1.0
Dynamic: author
Dynamic: home-page
Dynamic: license-file
Dynamic: requires-python
